{
  "aquifers_enabled": true,
  "default_block": {
    "Name": "mia:abyss_andesite"
  },
  "default_fluid": {
    "Name": "minecraft:water",
    "Properties": {
      "level": "0"
    }
  },
  "disable_mob_generation": false,
  "legacy_random_source": false,
  "noise": {
    "height": 320,
    "min_y": -64,
    "size_horizontal": 4,
    "size_vertical": 4
  },
  "noise_router": {
    "barrier": {
      "type": "minecraft:noise",
      "noise": "minecraft:aquifer_barrier",
      "xz_scale": 1.0,
      "y_scale": 0.5
    },
    "continents": 0.0,
    "depth": "mia:abyss_edge/depth",
    "erosion": 0.0,
    "final_density": {
      "type": "minecraft:min",
      "argument1": {
        "type": "minecraft:squeeze",
        "argument": {
          "type": "minecraft:mul",
          "argument1": 0.64,
          "argument2": {
            "type": "minecraft:interpolated",
            "argument": {
              "type": "minecraft:blend_density",
              "argument": {
                "type": "minecraft:add",
                "argument1": -0.4,
                "argument2": {
                  "type": "minecraft:mul",
                  "argument1": {
                    "type": "minecraft:y_clamped_gradient",
                    "from_value": 0.0,
                    "from_y": -16,
                    "to_value": 1.0,
                    "to_y": 16
                  },
                  "argument2": {
                    "type": "minecraft:add",
                    "argument1": 0.4,
                    "argument2": {
                      "type": "minecraft:add",
                      "argument1": 1.5625,
                      "argument2": {
                        "type": "minecraft:mul",
                        "argument1": {
                          "type": "minecraft:y_clamped_gradient",
                          "from_value": 1.0,
                          "from_y": 192,
                          "to_value": 0.0,
                          "to_y": 240
                        },
                        "argument2": {
                          "type": "minecraft:add",
                          "argument1": -1.025,
                          "argument2": {
                            "type": "minecraft:range_choice",
                            "input": "mia:temptation_forest/abyss_hole",
                            "max_exclusive": 0.025,
                            "min_inclusive": -1000000.0,
                            "when_in_range": "mia:temptation_forest/inside_abyss_hole",
                            "when_out_of_range": {
                              "type": "minecraft:range_choice",
                              "input": "minecraft:overworld/sloped_cheese",
                              "max_exclusive": 1.5625,
                              "min_inclusive": -1000000.0,
                              "when_in_range": {
                                "type": "minecraft:min",
                                "argument1": "minecraft:overworld/sloped_cheese",
                                "argument2": {
                                  "type": "minecraft:mul",
                                  "argument1": "minecraft:overworld/caves/spaghetti_2d",
                                  "argument2": "minecraft:overworld/caves/entrances"
                                }
                              },
                              "when_out_of_range": {
                                "type": "minecraft:max",
                                "argument1": {
                                  "type": "minecraft:min",
                                  "argument1": "minecraft:overworld/caves/entrances",
                                  "argument2": {
                                    "type": "minecraft:add",
                                    "argument1": "minecraft:overworld/caves/spaghetti_2d",
                                    "argument2": "minecraft:overworld/caves/spaghetti_roughness_function"
                                  }
                                },
                                "argument2": "mia:abyss_edge/caves/abyss_pillars"
                              }
                            }
                          }
                        }
                      }
                    }
                  }
                }
              }
            }
          }
        }
      },
      "argument2": "mia:temptation_forest/caves/noodle"
    },
    "fluid_level_floodedness": 0.0,
    "fluid_level_spread": 0.0,
    "initial_density_without_jaggedness": 0.0,
    "lava": 0.0,
    "ridges": "minecraft:overworld/ridges",
    "temperature": {
      "type": "minecraft:shifted_noise",
      "noise": "minecraft:temperature",
      "shift_x": "minecraft:shift_x",
      "shift_y": 0.0,
      "shift_z": "minecraft:shift_z",
      "xz_scale": 0.25,
      "y_scale": 0.0
    },
    "vegetation": {
      "type": "minecraft:shifted_noise",
      "noise": "minecraft:vegetation",
      "shift_x": "minecraft:shift_x",
      "shift_y": 0.0,
      "shift_z": "minecraft:shift_z",
      "xz_scale": 0.25,
      "y_scale": 0.0
    },
    "vein_gap": 0.0,
    "vein_ridged": 0.0,
    "vein_toggle": 0.0
  },
  "ore_veins_enabled": true,
  "sea_level": -128,
  "spawn_target": [],
  "surface_rule": {
    "type": "minecraft:sequence",
    "sequence": [
      {
        "type": "minecraft:condition",
        "if_true": {
          "type": "minecraft:not",
          "invert": {
            "type": "minecraft:vertical_gradient",
            "false_at_and_above": {
              "below_top": 0
            },
            "random_name": "minecraft:deepslate_roof",
            "true_at_and_below": {
              "below_top": 5
            }
          }
        },
        "then_run": {
          "type": "minecraft:block",
          "result_state": {
            "Name": "minecraft:bedrock"
          }
        }
      },
      {
        "type": "minecraft:sequence",
        "sequence": [
          {
            "type": "minecraft:condition",
            "if_true": {
              "type": "minecraft:biome",
              "biome_is": [
                "mia:abyss_edge/abyss_edge",
                "mia:abyss_edge/skyfog_forest",
                "mia:abyss_edge/abyss_plains",
                "mia:abyss_edge/prasiolite_caves",
                "mia:abyss_edge/abyss_lush_caves",
                "minecraft:cherry_grove"
              ]
            },
            "then_run": {
              "type": "minecraft:sequence",
              "sequence": [
                {
                  "type": "minecraft:condition",
                  "if_true": {
                    "type": "minecraft:stone_depth",
                    "add_surface_depth": false,
                    "offset": 0,
                    "secondary_depth_range": 0,
                    "surface_type": "floor"
                  },
                  "then_run": {
                    "type": "minecraft:condition",
                    "if_true": {
                      "type": "minecraft:water",
                      "add_stone_depth": false,
                      "offset": 0,
                      "surface_depth_multiplier": 0
                    },
                    "then_run": {
                      "type": "minecraft:block",
                      "result_state": {
                        "Name": "mia:covergrass_abyss_andesite"
                      }
                    }
                  }
                }
              ]
            }
          },
          {
            "type": "minecraft:condition",
            "if_true": {
              "type": "minecraft:biome",
              "biome_is": [
                "mia:abyss_edge/abyss_dripstone_caves"
              ]
            },
            "then_run": {
              "type": "minecraft:sequence",
              "sequence": [
                {
                  "type": "minecraft:condition",
                  "if_true": {
                    "type": "minecraft:stone_depth",
                    "add_surface_depth": false,
                    "offset": 0,
                    "secondary_depth_range": 0,
                    "surface_type": "floor"
                  },
                  "then_run": {
                    "type": "minecraft:condition",
                    "if_true": {
                      "type": "minecraft:water",
                      "add_stone_depth": false,
                      "offset": 0,
                      "surface_depth_multiplier": 0
                    },
                    "then_run": {
                      "type": "minecraft:block",
                      "result_state": {
                        "Name": "mia:covergrass_tuff"
                      }
                    }
                  }
                },
                {
                  "type": "minecraft:block",
                  "result_state": {
                    "Name": "minecraft:tuff"
                  }
                }
              ]
            }
          }
        ]
      }
    ]
  }
}